CHANGES.txt
LICENSE.txt
MANIFEST.in
README.txt
setup.py
js/__init__.py
js.jqueryui_touch_punch.egg-info/PKG-INFO
js.jqueryui_touch_punch.egg-info/SOURCES.txt
js.jqueryui_touch_punch.egg-info/dependency_links.txt
js.jqueryui_touch_punch.egg-info/entry_points.txt
js.jqueryui_touch_punch.egg-info/namespace_packages.txt
js.jqueryui_touch_punch.egg-info/not-zip-safe
js.jqueryui_touch_punch.egg-info/requires.txt
js.jqueryui_touch_punch.egg-info/top_level.txt
js/jqueryui_touch_punch/__init__.py
js/jqueryui_touch_punch/test_jquery_ui_touch_punch.txt
js/jqueryui_touch_punch/resources/jquery.ui.touch-punch.js
js/jqueryui_touch_punch/resources/jquery.ui.touch-punch.min.js