Metadata-Version: 1.0
Name: js.jqueryui-touch-punch
Version: 0.2.2
Summary: Fanstatic packaging of jQuery UI Touch Punch
Home-page: UNKNOWN
Author: Fanstatic Developers
Author-email: fanstatic@googlegroups.com
License: BSD
Platform: UNKNOWN
